pronunciation_dictionary/__init__.py
pronunciation_dictionary/deserialization.py
pronunciation_dictionary/io.py
pronunciation_dictionary/mp_options.py
pronunciation_dictionary/phoneme_set_extraction.py
pronunciation_dictionary/pronunciation_selection.py
pronunciation_dictionary/serialization.py
pronunciation_dictionary/types.py
pronunciation_dictionary/validation.py
pronunciation_dictionary-0.0.6.dist-info/LICENSE
pronunciation_dictionary-0.0.6.dist-info/METADATA
pronunciation_dictionary-0.0.6.dist-info/WHEEL
pronunciation_dictionary-0.0.6.dist-info/top_level.txt
pronunciation_dictionary-0.0.6.dist-info/RECORD
